org_ical/export.py
org_ical/ics_gcal.py
org_ical/utils.py
org_ical-0.1.0.dist-info/WHEEL
org_ical-0.1.0.dist-info/METADATA
org_ical-0.1.0.dist-info/RECORD
