Metadata-Version: 2.1
Name: org-ical
Version: 0.1.0
Summary: Sync your org files to ical provider
Author: Aleksandar Ivanovski
Author-email: aleksandar.ivanovski123@gmail.com
Requires-Python: >=3.9,<4.0
Classifier: Programming Language :: Python :: 3
Classifier: Programming Language :: Python :: 3.10
Classifier: Programming Language :: Python :: 3.9
Requires-Dist: bs4 (>=0.0.1,<0.0.2)
Requires-Dist: google-api-python-client (>=2.64.0,<3.0.0)
Requires-Dist: httplib2 (>=0.20.4,<0.21.0)
Requires-Dist: icalendar (>=4.1.0,<5.0.0)
Requires-Dist: oauth2client (>=4.1.3,<5.0.0)
Requires-Dist: omegaconf (>=2.2.3,<3.0.0)
Requires-Dist: tzlocal (>=4.2,<5.0)
